README.md
setup.cfg
setup.py
eloquent_depthai/DepthCamera.py
eloquent_depthai/__init__.py
eloquent_depthai.egg-info/PKG-INFO
eloquent_depthai.egg-info/SOURCES.txt
eloquent_depthai.egg-info/dependency_links.txt
eloquent_depthai.egg-info/requires.txt
eloquent_depthai.egg-info/top_level.txt