Metadata-Version: 2.1
Name: eloquent-depthai
Version: 0.0.2
Summary: Eloquent interface to Luxonis DepthAI cameras
Home-page: https://github.com/eloquentarduino/eloquent_depthai
Download-URL: https://github.com/eloquentarduino/eloquent_depthai/blob/master/dist/eloquent_depthai-0.0.2.tar.gz?raw=true
Author: Eloquent Arduino
Author-email: support@eloquentarduino.com
License: MIT
Keywords: CV,Computer Vision
Platform: UNKNOWN
Classifier: Development Status :: 2 - Pre-Alpha
Classifier: Intended Audience :: Developers
Classifier: License :: OSI Approved :: MIT License
Classifier: Programming Language :: Python :: 3
Classifier: Programming Language :: Python :: 3.4
Classifier: Programming Language :: Python :: 3.5
Classifier: Programming Language :: Python :: 3.6
